stdpe/__init__.py
stdpe/azure/__init__.py
stdpe/azure/blob_manager.py
stdpe/azure/key_vault.py
stdpe/db_kit/__init__.py
stdpe/db_kit/ms_sql.py
stdpe/db_kit/orm_models.py
stdpe/utils/__init__.py
stdpe/utils/dict_utils.py
stdpe/utils/logger.py
stdpe/utils/pd_utils.py
stdpe/utils/stopwatch.py
stdpe/utils/thread.py
stdpe/utils/wgs.py
stdpe-0.0.8.dist-info/LICENSE
stdpe-0.0.8.dist-info/METADATA
stdpe-0.0.8.dist-info/WHEEL
stdpe-0.0.8.dist-info/top_level.txt
stdpe-0.0.8.dist-info/RECORD
